{
  "name": "UiAssistantMessage",
  "canonicalReference": "@hashbrownai/react!UiAssistantMessage:type",
  "kind": "TypeAlias",
  "fileUrlPath": "../dist/packages/react/hooks/use-ui-chat.d.ts",
  "isDeprecated": false,
  "members": [
    {
      "kind": "TypeAlias",
      "canonicalReference": "@hashbrownai/react!UiAssistantMessage:type",
      "docComment": "",
      "excerptTokens": [
        {
          "kind": "Content",
          "text": "export type UiAssistantMessage<Tools extends "
        },
        {
          "kind": "Reference",
          "text": "Chat.AnyTool",
          "canonicalReference": "!Chat.AnyTool:type"
        },
        { "kind": "Content", "text": "> = " },
        {
          "kind": "Reference",
          "text": "Chat.AssistantMessage",
          "canonicalReference": "!Chat.AssistantMessage:type"
        },
        { "kind": "Content", "text": "<typeof " },
        {
          "kind": "Reference",
          "text": "publicSchema",
          "canonicalReference": "@hashbrownai/react!~publicSchema:var"
        },
        { "kind": "Content", "text": ", Tools> & {\n    ui: " },
        {
          "kind": "Reference",
          "text": "React.ReactElement",
          "canonicalReference": "!React.ReactElement:type"
        },
        { "kind": "Content", "text": "[] | null;\n}" },
        { "kind": "Content", "text": ";" }
      ],
      "fileUrlPath": "../dist/packages/react/hooks/use-ui-chat.d.ts",
      "releaseTag": "Public",
      "name": "UiAssistantMessage",
      "typeParameters": [
        {
          "typeParameterName": "Tools",
          "constraintTokenRange": { "startIndex": 1, "endIndex": 2 },
          "defaultTypeTokenRange": { "startIndex": 0, "endIndex": 0 }
        }
      ],
      "typeTokenRange": { "startIndex": 3, "endIndex": 9 },
      "docs": {
        "modifiers": {
          "isInternal": false,
          "isPublic": false,
          "isAlpha": false,
          "isBeta": false,
          "isOverride": false,
          "isExperimental": false
        },
        "summary": "",
        "usageNotes": "",
        "remarks": "",
        "deprecated": "",
        "returns": "",
        "see": [],
        "params": []
      }
    }
  ]
}
