{
  "name": "SystemPrompt",
  "canonicalReference": "@hashbrownai/core!SystemPrompt:type",
  "kind": "TypeAlias",
  "fileUrlPath": "../packages/core/src/prompt/types.ts",
  "isDeprecated": false,
  "members": [
    {
      "kind": "TypeAlias",
      "canonicalReference": "@hashbrownai/core!SystemPrompt:type",
      "docComment": "",
      "excerptTokens": [
        { "kind": "Content", "text": "export type SystemPrompt = " },
        {
          "kind": "Content",
          "text": "{\n    compile: (components: readonly any[], schema: "
        },
        {
          "kind": "Reference",
          "text": "HashbrownType",
          "canonicalReference": "@hashbrownai/core!s.HashbrownType:interface"
        },
        { "kind": "Content", "text": ") => string;\n    examples: " },
        {
          "kind": "Reference",
          "text": "HBTree",
          "canonicalReference": "@hashbrownai/core!HBTree:type"
        },
        { "kind": "Content", "text": "[];\n    diagnostics: " },
        {
          "kind": "Reference",
          "text": "PromptDiagnostic",
          "canonicalReference": "@hashbrownai/core!PromptDiagnostic:interface"
        },
        { "kind": "Content", "text": "[];\n    meta: {\n        uiBlocks: " },
        {
          "kind": "Reference",
          "text": "Array",
          "canonicalReference": "!Array:interface"
        },
        {
          "kind": "Content",
          "text": "<{\n            start: number;\n            end: number;\n            source: string;\n        }>;\n    };\n}"
        },
        { "kind": "Content", "text": ";" }
      ],
      "fileUrlPath": "../packages/core/src/prompt/types.ts",
      "releaseTag": "Public",
      "name": "SystemPrompt",
      "typeTokenRange": { "startIndex": 1, "endIndex": 10 },
      "docs": {
        "modifiers": {
          "isInternal": false,
          "isPublic": false,
          "isAlpha": false,
          "isBeta": false,
          "isOverride": false,
          "isExperimental": false
        },
        "summary": "",
        "usageNotes": "",
        "remarks": "",
        "deprecated": "",
        "returns": "",
        "see": [],
        "params": [],
        "examples": []
      },
      "formattedContent": "export type SystemPrompt = {\n  compile: (\n    components: readonly any[],\n    schema:  HashbrownType ,\n  ) => string;\n  examples:  HBTree [];\n  diagnostics:  PromptDiagnostic [];\n  meta: {\n    uiBlocks:  Array <{\n      start: number;\n      end: number;\n      source: string;\n    }>;\n  };\n};",
      "overlayTokens": [
        {
          "kind": "Content",
          "text": "export type SystemPrompt = {\n  compile: (\n    components: readonly any[],\n    schema: "
        },
        {
          "kind": "Reference",
          "text": " HashbrownType ",
          "canonicalReference": "@hashbrownai/core!s.HashbrownType:interface"
        },
        { "kind": "Content", "text": ",\n  ) => string;\n  examples: " },
        {
          "kind": "Reference",
          "text": " HBTree ",
          "canonicalReference": "@hashbrownai/core!HBTree:type"
        },
        { "kind": "Content", "text": "[];\n  diagnostics: " },
        {
          "kind": "Reference",
          "text": " PromptDiagnostic ",
          "canonicalReference": "@hashbrownai/core!PromptDiagnostic:interface"
        },
        { "kind": "Content", "text": "[];\n  meta: {\n    uiBlocks: " },
        {
          "kind": "Reference",
          "text": " Array",
          "canonicalReference": "!Array:interface"
        },
        {
          "kind": "Content",
          "text": " <{\n      start: number;\n      end: number;\n      source: string;\n    }>;\n  };\n};"
        }
      ]
    }
  ]
}
